ca_kit-0.2.1.data/scripts/ck_create
ca_kit-0.2.1.data/scripts/ck_create_ca
ca_kit-0.2.1.data/scripts/ck_sign
ca_kit-0.2.1.data/scripts/ck_verify_ca
ca_kit-0.2.1.dist-info/DESCRIPTION.rst
ca_kit-0.2.1.dist-info/METADATA
ca_kit-0.2.1.dist-info/metadata.json
ca_kit-0.2.1.dist-info/RECORD
ca_kit-0.2.1.dist-info/top_level.txt
ca_kit-0.2.1.dist-info/WHEEL
ck/__init__.py
ck/ssl_library.py
ck/resources/README.rst
ck/resources/requirements.txt
ck/resources/scripts/ck_create
ck/resources/scripts/ck_create_ca
ck/resources/scripts/ck_sign
ck/resources/scripts/ck_verify_ca
