Metadata-Version: 2.0
Name: ca-kit
Version: 0.2.1
Summary: Certificate-authority test harness.
Home-page: https://github.com/dsoprea/CaKit
Author: Dustin Oprea
Author-email: myselfasunder@gmail.com
License: GPL 2
Keywords: ssl openssl ca certificate
Platform: UNKNOWN
Requires-Dist: M2Crypto (==0.22.3)
Requires-Dist: wsgiref (==0.1.2)
